featurewiz_polars/__init__.py
featurewiz_polars/__version__.py
featurewiz_polars/featurewiz_polars.py
featurewiz_polars/polars_categorical_encoder.py
featurewiz_polars/polars_datetime_transformer.py
featurewiz_polars/polars_other_transformers.py
featurewiz_polars/polars_sulov_mrmr.py
featurewiz_polars/print_metrics.py
featurewiz_polars-0.3.0.dist-info/LICENSE
featurewiz_polars-0.3.0.dist-info/METADATA
featurewiz_polars-0.3.0.dist-info/WHEEL
featurewiz_polars-0.3.0.dist-info/top_level.txt
featurewiz_polars-0.3.0.dist-info/RECORD
