Metadata-Version: 2.2
Name: featurewiz_polars
Version: 0.3.0
Summary: Fast feature selection using MRMR algorithm and Polars for large datasets.
Home-page: https://github.com/AutoViML/featurewiz_polars
Author: Ram Seshadri
License: Apache License 2.0
Classifier: Programming Language :: Python :: 3
Classifier: Operating System :: OS Independent
License-File: LICENSE
Requires-Dist: numpy<2.0
Requires-Dist: pandas>=1.2.4
Requires-Dist: scipy
Requires-Dist: scikit-learn>=1.2.2
Requires-Dist: xgboost>=1.6
Requires-Dist: polars>=1.23.0
Requires-Dist: pyarrow
Requires-Dist: kneed
Dynamic: author
Dynamic: classifier
Dynamic: description
Dynamic: description-content-type
Dynamic: home-page
Dynamic: license
Dynamic: requires-dist
Dynamic: summary
